hyapi/__init__.py
hyapi/client.py
pyhyapi-0.1.3.dist-info/licenses/LICENSE
pyhyapi-0.1.3.dist-info/METADATA
pyhyapi-0.1.3.dist-info/WHEEL
pyhyapi-0.1.3.dist-info/top_level.txt
pyhyapi-0.1.3.dist-info/RECORD
