Metadata-Version: 2.4
Name: pyhyapi
Version: 0.1.3
Summary: HyAPI - Python wrapper for Hypixel API
Home-page: https://github.com/Sm1CKBall/HyAPI
Author: Sm1CKBall
Author-email: sm1ckxmine@gmail.com
License: MIT
Classifier: Programming Language :: Python :: 3
Classifier: License :: OSI Approved :: MIT License
Classifier: Operating System :: OS Independent
Requires-Python: >=3.9
License-File: LICENSE
Requires-Dist: aiohttp
Dynamic: license-file
